tex2typ/__init__.py
tex2typ/__main__.py
tex2typ/equation_converter.py
tex2typ/image_generator.py
tex2typ/validator.py
tex2typ/templates/math_test.typ
tex2typ/templates/math_to_image.typ
tex2typ-0.0.3.dist-info/METADATA
tex2typ-0.0.3.dist-info/WHEEL
tex2typ-0.0.3.dist-info/entry_points.txt
tex2typ-0.0.3.dist-info/licenses/LICENSE
tex2typ-0.0.3.dist-info/RECORD
