Metadata-Version: 2.4
Name: tex2typ
Version: 0.0.3
Summary: A Python CLI tool for converting LaTeX equations into Typst equations
Project-URL: Homepage, https://Niels-Skovgaard-Jensen.github.io/tex2typ/
Project-URL: Repository, https://github.com/Niels-Skovgaard-Jensen/tex2typ
Project-URL: Documentation, https://Niels-Skovgaard-Jensen.github.io/tex2typ/
Author-email: Niels Skovgaard Jensen <nsj@ticra.com>
License-File: LICENSE
Keywords: python
Classifier: Intended Audience :: Developers
Classifier: Programming Language :: Python
Classifier: Programming Language :: Python :: 3
Classifier: Programming Language :: Python :: 3.10
Classifier: Programming Language :: Python :: 3.11
Classifier: Programming Language :: Python :: 3.12
Classifier: Programming Language :: Python :: 3.13
Classifier: Topic :: Software Development :: Libraries :: Python Modules
Requires-Python: <4.0,>=3.10
Requires-Dist: pillow>=10.0.0
Requires-Dist: pypandoc>=1.14
Requires-Dist: pyperclip>=1.9.0
